beerializer/__init__.py
beerializer/base.py
beerializer/fields.py
beerializer/validators.py
beerializer-0.1.5.dist-info/DESCRIPTION.rst
beerializer-0.1.5.dist-info/METADATA
beerializer-0.1.5.dist-info/RECORD
beerializer-0.1.5.dist-info/WHEEL
beerializer-0.1.5.dist-info/metadata.json
beerializer-0.1.5.dist-info/top_level.txt
