Metadata-Version: 2.0
Name: beerializer
Version: 0.1.5
Summary: Package to convert arbitrary python objects into DTOs ready for serialization and validation. 
Home-page: https://github.com/Songbee/beerializer
Author: Songbee Team
Author-email: hi@songbee.net
License: UNKNOWN
Keywords: dto serializer serialize REST marshal JSON
Platform: UNKNOWN
Classifier: Development Status :: 4 - Beta
Classifier: Intended Audience :: Developers
Classifier: License :: Public Domain
Classifier: Programming Language :: Python
Classifier: Topic :: Internet :: WWW/HTTP :: Dynamic Content
Classifier: Topic :: Internet :: WWW/HTTP :: Dynamic Content :: CGI Tools/Libraries
Classifier: Topic :: Software Development
